README.md
setup.py
ecpc/__init__.py
ecpc/_instances.py
ecpc/_version.py
ecpc/commands.py
ecpc/configuration.py
ecpc/data.py
ecpc/metering.py
ecpc/utilities.py
ecpc.egg-info/PKG-INFO
ecpc.egg-info/SOURCES.txt
ecpc.egg-info/dependency_links.txt
ecpc.egg-info/requires.txt
ecpc.egg-info/top_level.txt
scripts/ecpc
test/test_data.py
test/test_utilities.py