Metadata-Version: 2.1
Name: ecpc
Version: 0.0.7
Summary: Simple scripts to launch EC2 instances
Home-page: https://bitbucket.org/claughton/ecpc
Author: Charlie Laughton
Author-email: charles.laughton@nottingham.ac.uk
License: UNKNOWN
Platform: UNKNOWN
Classifier: Programming Language :: Python :: 3
Classifier: License :: OSI Approved :: BSD License
Classifier: Development Status :: 3 - Alpha
